<annotation>
	<folder>resized</folder>
	<filename>resized_713.jpg</filename>
	<path>D:\Food Datasets\customDS\resized\resized_713.jpg</path>
	<source>
		<database>Unknown</database>
	</source>
	<size>
		<width>250</width>
		<height>250</height>
		<depth>3</depth>
	</size>
	<segmented>0</segmented>
	<object>
		<name>icecream</name>
		<pose>Unspecified</pose>
		<truncated>0</truncated>
		<difficult>0</difficult>
		<bndbox>
			<xmin>8</xmin>
			<ymin>174</ymin>
			<xmax>124</xmax>
			<ymax>241</ymax>
		</bndbox>
	</object>
	<object>
		<name>icecream</name>
		<pose>Unspecified</pose>
		<truncated>0</truncated>
		<difficult>0</difficult>
		<bndbox>
			<xmin>101</xmin>
			<ymin>149</ymin>
			<xmax>171</xmax>
			<ymax>208</ymax>
		</bndbox>
	</object>
	<object>
		<name>icecream</name>
		<pose>Unspecified</pose>
		<truncated>0</truncated>
		<difficult>0</difficult>
		<bndbox>
			<xmin>169</xmin>
			<ymin>129</ymin>
			<xmax>222</xmax>
			<ymax>171</ymax>
		</bndbox>
	</object>
</annotation>
